LICENSE
MANIFEST.in
README.txt
setup.py
pymailgunner/__init__.py
pymailgunner/client.py
pymailgunner.egg-info/PKG-INFO
pymailgunner.egg-info/SOURCES.txt
pymailgunner.egg-info/dependency_links.txt
pymailgunner.egg-info/requires.txt
pymailgunner.egg-info/top_level.txt