Metadata-Version: 1.1
Name: pymailgunner
Version: 1.4
Summary: A simple mailgun client - pymailgun fork with Python 3 support
Home-page: https://github.com/pschmitt/pymailgunner
Author: Philipp Schmitt
Author-email: philipp@schmitt.co
License: Apache license version 2.0
Download-URL: https://github.com/pschmitt/pymailgunner/archive/master.zip
Platform: OS Independent
Classifier: Programming Language :: Python
Classifier: Programming Language :: Python :: 2.7
Classifier: Programming Language :: Python :: 3
Classifier: Intended Audience :: Developers
Classifier: License :: OSI Approved :: Apache Software License
Classifier: Operating System :: OS Independent
Classifier: Topic :: Software Development :: Libraries :: Python Modules
Classifier: Environment :: Web Environment
